cortex/__init__.py
cortex/__main__.py
cortex/config.py
cortex/conversation_manager.py
cortex/gpu_validator.py
cortex/inference_engine.py
cortex/model_downloader.py
cortex/model_manager.py
cortex/fine_tuning/__init__.py
cortex/fine_tuning/dataset.py
cortex/fine_tuning/mlx_lora_trainer.py
cortex/fine_tuning/trainer.py
cortex/fine_tuning/wizard.py
cortex/metal/__init__.py
cortex/metal/gpu_validator.py
cortex/metal/memory_pool.py
cortex/metal/mlx_accelerator.py
cortex/metal/mlx_compat.py
cortex/metal/mlx_converter.py
cortex/metal/mps_optimizer.py
cortex/metal/optimizer.py
cortex/metal/performance_profiler.py
cortex/quantization/__init__.py
cortex/quantization/dynamic_quantizer.py
cortex/template_registry/__init__.py
cortex/template_registry/auto_detector.py
cortex/template_registry/config_manager.py
cortex/template_registry/interactive.py
cortex/template_registry/registry.py
cortex/template_registry/template_profiles/__init__.py
cortex/template_registry/template_profiles/base.py
cortex/template_registry/template_profiles/complex/__init__.py
cortex/template_registry/template_profiles/complex/reasoning.py
cortex/template_registry/template_profiles/standard/__init__.py
cortex/template_registry/template_profiles/standard/alpaca.py
cortex/template_registry/template_profiles/standard/chatml.py
cortex/template_registry/template_profiles/standard/gemma.py
cortex/template_registry/template_profiles/standard/llama.py
cortex/template_registry/template_profiles/standard/simple.py
cortex/ui/__init__.py
cortex/ui/cli.py
cortex/ui/markdown_render.py
cortex/ui/terminal_app.py
cortex_llm-1.0.6.dist-info/licenses/LICENSE
cortex_llm-1.0.6.dist-info/METADATA
cortex_llm-1.0.6.dist-info/WHEEL
cortex_llm-1.0.6.dist-info/entry_points.txt
cortex_llm-1.0.6.dist-info/top_level.txt
cortex_llm-1.0.6.dist-info/RECORD
