Metadata-Version: 2.4
Name: cortex-llm
Version: 1.0.6
Summary: GPU-Accelerated LLM Terminal for Apple Silicon
Home-page: https://github.com/faisalmumtaz/Cortex
Author: Cortex Development Team
License-Expression: MIT
Project-URL: Homepage, https://github.com/faisalmumtaz/Cortex
Project-URL: Bug Tracker, https://github.com/faisalmumtaz/Cortex/issues
Project-URL: Documentation, https://github.com/faisalmumtaz/Cortex/wiki
Keywords: llm,gpu,metal,mps,apple-silicon,ai,machine-learning,terminal,mlx,pytorch
Platform: darwin
Classifier: Development Status :: 4 - Beta
Classifier: Intended Audience :: Developers
Classifier: Topic :: Scientific/Engineering :: Artificial Intelligence
Classifier: Programming Language :: Python :: 3
Classifier: Programming Language :: Python :: 3.11
Classifier: Programming Language :: Python :: 3.12
Classifier: Operating System :: MacOS
Classifier: Environment :: Console
Classifier: Environment :: GPU
Requires-Python: >=3.11
License-File: LICENSE
Requires-Dist: torch>=2.1.0
Requires-Dist: mlx>=0.30.4
Requires-Dist: mlx-lm>=0.30.5
Requires-Dist: transformers>=4.36.0
Requires-Dist: safetensors>=0.4.0
Requires-Dist: huggingface-hub>=0.19.0
Requires-Dist: accelerate>=0.25.0
Requires-Dist: llama-cpp-python>=0.2.0
Requires-Dist: pyyaml>=6.0
Requires-Dist: pydantic>=2.5.0
Requires-Dist: rich>=13.0.0
Requires-Dist: psutil>=5.9.0
Requires-Dist: numpy>=1.24.0
Requires-Dist: packaging>=23.0
Requires-Dist: requests>=2.31.0
Provides-Extra: dev
Requires-Dist: pytest>=7.4.0; extra == "dev"
Requires-Dist: pytest-asyncio>=0.21.0; extra == "dev"
Requires-Dist: black>=23.0.0; extra == "dev"
Requires-Dist: ruff>=0.1.0; extra == "dev"
Requires-Dist: mypy>=1.8.0; extra == "dev"
Provides-Extra: optional
Requires-Dist: sentencepiece>=0.1.99; extra == "optional"
Requires-Dist: auto-gptq>=0.7.0; extra == "optional"
Requires-Dist: autoawq>=0.2.0; extra == "optional"
Requires-Dist: bitsandbytes>=0.41.0; extra == "optional"
Requires-Dist: optimum>=1.16.0; extra == "optional"
Requires-Dist: torchvision>=0.16.0; extra == "optional"
Requires-Dist: torchaudio>=2.1.0; extra == "optional"
Dynamic: home-page
Dynamic: license-file
Dynamic: platform
Dynamic: requires-python
